passeo/__init__.py
passeo/main.py
passeo-1.1.3.dist-info/LICENSE
passeo-1.1.3.dist-info/METADATA
passeo-1.1.3.dist-info/WHEEL
passeo-1.1.3.dist-info/entry_points.txt
passeo-1.1.3.dist-info/top_level.txt
passeo-1.1.3.dist-info/RECORD
