Metadata-Version: 2.1
Name: passeo
Version: 1.1.3
Summary: 🔓 Generate a Password with multiple options
Home-page: https://github.com/ArjunSharda/Passeo
Author: Arjun Sharda
Author-email: Arjun Sharda <sharda.aj17@gmail.com>
License: MIT License
Project-URL: Homepage, https://github.com/ArjunSharda/Passeo
Project-URL: Bug Tracker, https://github.com/ArjunSharda/Passeo/issues
Classifier: Programming Language :: Python :: 3
Classifier: License :: OSI Approved :: MIT License
Classifier: Operating System :: OS Independent
Requires-Python: >=3.7, <4
License-File: LICENSE
Requires-Dist: click
Requires-Dist: requests
Requires-Dist: aenum
